LICENSE.rst
MANIFEST.in
README.rst
setup.cfg
setup.py
tox.ini
git_ls_anytree/VERSION
git_ls_anytree/__init__.py
git_ls_anytree/__main__.py
git_ls_anytree/__version__.py
git_ls_anytree/cli_file.py
git_ls_anytree/convert_path_to_list.py
git_ls_anytree/git_ls_tree.py
git_ls_anytree/git_ls_tree_node.py
git_ls_anytree/local_exceptions.py
git_ls_anytree.egg-info/PKG-INFO
git_ls_anytree.egg-info/SOURCES.txt
git_ls_anytree.egg-info/dependency_links.txt
git_ls_anytree.egg-info/entry_points.txt
git_ls_anytree.egg-info/top_level.txt