Metadata-Version: 1.1
Name: git-ls-anytree
Version: 0.4.1
Summary: Runs git-ls-tree through anytree for easy consumption
Home-page: https://github.com/wizardsoftheweb/git-ls-anytree#readme
Author: CJ Harries
Author-email: cj@wizardsoftheweb.pro
License: ISC
Platform: UNKNOWN
Requires: anytree
